ChessAI/Icon.ico
ChessAI/__init__.py
ChessAI/chessai.cmd
ChessAI/engine.py
ChessAI/gui.py
ChessAI/main.py
ChessAI/setting.json
ChessAI/train.py
ChessAI/vision.py
ChessAI/Templates/Chesscom/Black_Bishop_1.png
ChessAI/Templates/Chesscom/Black_Bishop_2.png
ChessAI/Templates/Chesscom/Black_King_1.png
ChessAI/Templates/Chesscom/Black_King_2.png
ChessAI/Templates/Chesscom/Black_Knight_1.png
ChessAI/Templates/Chesscom/Black_Knight_2.png
ChessAI/Templates/Chesscom/Black_Pawn_1.png
ChessAI/Templates/Chesscom/Black_Pawn_2.png
ChessAI/Templates/Chesscom/Black_Queen_1.png
ChessAI/Templates/Chesscom/Black_Queen_2.png
ChessAI/Templates/Chesscom/Black_Rook_1.png
ChessAI/Templates/Chesscom/Black_Rook_2.png
ChessAI/Templates/Chesscom/Chessboard.png
ChessAI/Templates/Chesscom/Empty_1.png
ChessAI/Templates/Chesscom/Empty_2.png
ChessAI/Templates/Chesscom/Info.json
ChessAI/Templates/Chesscom/Labels.csv
ChessAI/Templates/Chesscom/White_Bishop_1.png
ChessAI/Templates/Chesscom/White_Bishop_2.png
ChessAI/Templates/Chesscom/White_King_1.png
ChessAI/Templates/Chesscom/White_King_2.png
ChessAI/Templates/Chesscom/White_Knight_1.png
ChessAI/Templates/Chesscom/White_Knight_2.png
ChessAI/Templates/Chesscom/White_Pawn_1.png
ChessAI/Templates/Chesscom/White_Pawn_2.png
ChessAI/Templates/Chesscom/White_Queen_1.png
ChessAI/Templates/Chesscom/White_Queen_2.png
ChessAI/Templates/Chesscom/White_Rook_1.png
ChessAI/Templates/Chesscom/White_Rook_2.png
ChessAI/Templates/Chesscom/model.pth
ChessAI/UI_Assets/black_bishop.png
ChessAI/UI_Assets/black_chessboard.png
ChessAI/UI_Assets/black_king.png
ChessAI/UI_Assets/black_knight.png
ChessAI/UI_Assets/black_pawn.png
ChessAI/UI_Assets/black_queen.png
ChessAI/UI_Assets/black_rook.png
ChessAI/UI_Assets/black_side.png
ChessAI/UI_Assets/deselect.png
ChessAI/UI_Assets/empty.png
ChessAI/UI_Assets/flip.png
ChessAI/UI_Assets/kill.png
ChessAI/UI_Assets/move.png
ChessAI/UI_Assets/redo.png
ChessAI/UI_Assets/undo.png
ChessAI/UI_Assets/vision_add.png
chessai_stockfish-1.0.3.dist-info/LICENSE
chessai_stockfish-1.0.3.dist-info/METADATA
chessai_stockfish-1.0.3.dist-info/WHEEL
chessai_stockfish-1.0.3.dist-info/entry_points.txt
chessai_stockfish-1.0.3.dist-info/top_level.txt
chessai_stockfish-1.0.3.dist-info/RECORD
