Metadata-Version: 2.1
Name: chessai-stockfish
Version: 1.0.3
Summary: A sub-window GUI for Stockfish. (Contributions are welcomed, but I might won't touch this any sooner)
Author: Linos
Project-URL: Source, https://github.com/Linos1391/ChessAI-StockfishGUI
Classifier: Development Status :: 5 - Production/Stable
Classifier: Programming Language :: Python :: 3.10
Classifier: Programming Language :: Python :: 3.11
Classifier: Programming Language :: Python :: 3.12
Classifier: Natural Language :: English
Classifier: Intended Audience :: End Users/Desktop
Classifier: License :: OSI Approved :: GNU General Public License v3 (GPLv3)
Classifier: Environment :: Console
Classifier: Environment :: GPU :: NVIDIA CUDA
Classifier: Operating System :: Microsoft :: Windows
Classifier: Operating System :: Unix
Requires-Python: >=3.10
License-File: LICENSE
Requires-Dist: pygubu
Requires-Dist: stockfish
Requires-Dist: Pillow
Requires-Dist: PyScreeze
